LICENSE
setup.py
rtfuc/__init__.py
rtfuc/__main__.py
rtfuc.egg-info/PKG-INFO
rtfuc.egg-info/SOURCES.txt
rtfuc.egg-info/dependency_links.txt
rtfuc.egg-info/entry_points.txt
rtfuc.egg-info/top_level.txt