Metadata-Version: 2.1
Name: rtfuc
Version: 1.1
Summary: Improves RTF files for catdoc and unrtf
Home-page: UNKNOWN
Author: Silas S. Brown
Author-email: ssb22@cam.ac.uk
License: Apache 2
Platform: any
Classifier: Programming Language :: Python :: 3
Classifier: License :: OSI Approved :: Apache Software License
Classifier: Operating System :: OS Independent
Requires-Python: >=3.8
License-File: LICENSE
